LICENSE
stqdm/__init__.py
stqdm/stqdm.py
stqdm-0.0.3.dist-info/LICENSE
stqdm-0.0.3.dist-info/WHEEL
stqdm-0.0.3.dist-info/METADATA
stqdm-0.0.3.dist-info/RECORD
