Metadata-Version: 2.1
Name: stqdm
Version: 0.0.3
Summary: Easy progress bar for streamlit based on the awesome streamlit.progress and tqdm
Home-page: https://github.com/Wirg/stqdm
License: Apache-2.0
Keywords: streamlit,progressbar,progressmeter,progress,bar,meter,rate,eta,tqdm
Author: Wirg
Requires-Python: >=3.6,<4.0
Classifier: License :: OSI Approved :: Apache Software License
Classifier: Operating System :: OS Independent
Classifier: Programming Language :: Python :: 3
Classifier: Programming Language :: Python :: 3.6
Classifier: Programming Language :: Python :: 3.7
Classifier: Programming Language :: Python :: 3.8
Classifier: Programming Language :: Python :: 3.9
Classifier: Topic :: Software Development :: Libraries :: Python Modules
Requires-Dist: streamlit (>=0.66)
Requires-Dist: tqdm (>=4.50)
Project-URL: Repository, https://github.com/Wirg/stqdm
